CHANGES.rst
CONTRIBUTORS.rst
MANIFEST.in
README.rst
TODO.rst
VERSION
long-description.rst
setup.cfg
setup.py
docs/LICENSE.GPL
docs/LICENSE.rst
docs/Makefile
docs/conf.py
docs/conf.rst
docs/index.rst
docs/make.bat
docs/modules.rst
docs/setup.rst
docs/visaplan.plone.rst
docs/visaplan.plone.tools.functions.rst
docs/visaplan.plone.tools.rst
docs/visaplan.rst
src/visaplan/__init__.py
src/visaplan.plone.tools.egg-info/PKG-INFO
src/visaplan.plone.tools.egg-info/SOURCES.txt
src/visaplan.plone.tools.egg-info/dependency_links.txt
src/visaplan.plone.tools.egg-info/entry_points.txt
src/visaplan.plone.tools.egg-info/namespace_packages.txt
src/visaplan.plone.tools.egg-info/not-zip-safe
src/visaplan.plone.tools.egg-info/requires.txt
src/visaplan.plone.tools.egg-info/top_level.txt
src/visaplan/plone/__init__.py
src/visaplan/plone/tools/__init__.py
src/visaplan/plone/tools/_at0.py
src/visaplan/plone/tools/_at1.py
src/visaplan/plone/tools/_at2.py
src/visaplan/plone/tools/_at3.py
src/visaplan/plone/tools/_at4.py
src/visaplan/plone/tools/_at5.py
src/visaplan/plone/tools/_at6.py
src/visaplan/plone/tools/_dx4.py
src/visaplan/plone/tools/_dx5.py
src/visaplan/plone/tools/_have.py
src/visaplan/plone/tools/_idxnames.py
src/visaplan/plone/tools/attools.py
src/visaplan/plone/tools/brains.py
src/visaplan/plone/tools/cfg.py
src/visaplan/plone/tools/configure.zcml
src/visaplan/plone/tools/context.py
src/visaplan/plone/tools/context.py.orig
src/visaplan/plone/tools/decorators.py
src/visaplan/plone/tools/dxtools.py
src/visaplan/plone/tools/env.py
src/visaplan/plone/tools/forms.py
src/visaplan/plone/tools/functions.py
src/visaplan/plone/tools/indexes.py
src/visaplan/plone/tools/lock.py
src/visaplan/plone/tools/log.py
src/visaplan/plone/tools/mock.py
src/visaplan/plone/tools/mock_cfg.py
src/visaplan/plone/tools/profiles.zcml
src/visaplan/plone/tools/search.py
src/visaplan/plone/tools/seo.py
src/visaplan/plone/tools/setuphandlers.py
src/visaplan/plone/tools/strings.py
src/visaplan/plone/tools/zcmlgen.py
src/visaplan/plone/tools/groups/__init__.py
src/visaplan/plone/tools/groups/_data.py
src/visaplan/plone/tools/groups/_group.py
src/visaplan/plone/tools/groups/_group_pio.py
src/visaplan/plone/tools/groups/_helpers.py
src/visaplan/plone/tools/groups/_imports.py
src/visaplan/plone/tools/groups/_membership.py
src/visaplan/plone/tools/groups/_user.py
